plissken/VERSION
plissken/__init__.py
plissken/cli.py
plissken/file_operators.py
plissken/documents/__init__.py
plissken/documents/function.py
plissken/documents/helpers.py
plissken/documents/klass.py
plissken/documents/module.py
plissken/documents/package.py
plissken/documents/variable.py
plissken/templates/md.template
plissken-0.0.7.dist-info/LICENSE
plissken-0.0.7.dist-info/METADATA
plissken-0.0.7.dist-info/WHEEL
plissken-0.0.7.dist-info/entry_points.txt
plissken-0.0.7.dist-info/top_level.txt
plissken-0.0.7.dist-info/RECORD
