Metadata-Version: 2.1
Name: plissken
Version: 0.0.7
Summary: UNKNOWN
Home-page: https://gitlab.com/dylanbstorey/plissken
Author: dylanbstorey
Author-email: dylan.storey@gmail.com
License: GPLv3
Platform: UNKNOWN
Requires-Python: >=3
Requires-Dist: click (>7.0.0)
Requires-Dist: colander (==1.7.0)
Requires-Dist: redbaron (>=0.9.2)
Requires-Dist: jinja2 (>=2)
Provides-Extra: dev
Requires-Dist: future ; extra == 'dev'
Requires-Dist: pytest (==3.8.0) ; extra == 'dev'
Requires-Dist: pytest-cov (==2.6.0) ; extra == 'dev'
Requires-Dist: sphinx (==1.8.0) ; extra == 'dev'
Requires-Dist: sphinx-rtd-theme (==0.4.1) ; extra == 'dev'
Requires-Dist: angreal (>=0.7.0) ; extra == 'dev'
Requires-Dist: mypy (>=0.660) ; extra == 'dev'
Requires-Dist: lxml (==4.3.0) ; extra == 'dev'
Requires-Dist: black (==19.10b0) ; extra == 'dev'
Requires-Dist: pre-commit (==2.2.0) ; extra == 'dev'
